<CD-RAT><Entry><HWD>10\2\2\Review of Past tenses</HWD><Activity><MultipleChoice><Title>Review of Past tenses</Title><Instruction>Choose the correct option.</Instruction><ReferenceObject><ImageFile size="641,85" path="swf/unit10_2_acitv2.swf"></ImageFile></ReferenceObject><ContentMultipleChoice><ReferenceObject><Paragraph><PersonName><font face="Verdana" size="12" color="#000000">1<TAB></TAB></font></PersonName></Paragraph></ReferenceObject><Choices is-dropdown="0"><Choice>had arrive</Choice><Choice>was arriving</Choice><Choice is-correct="1">arrived</Choice></Choices><ReferenceObject><Paragraph><PersonName><font face="Verdana" size="2" color="#ffffff">E<TAB></TAB></font></PersonName></Paragraph></ReferenceObject><ReferenceObject><Paragraph><PersonName><font face="Verdana" size="12" color="#000000">2<TAB></TAB></font></PersonName></Paragraph></ReferenceObject><Choices is-dropdown="0"><Choice is-correct="1">had just walked</Choice><Choice>had walking</Choice><Choice>walked</Choice></Choices><ReferenceObject><Paragraph><PersonName><font face="Verdana" size="2" color="#ffffff">E<TAB></TAB></font></PersonName></Paragraph></ReferenceObject><ReferenceObject><Paragraph><PersonName><font face="Verdana" size="12" color="#000000">3<TAB></TAB></font></PersonName></Paragraph></ReferenceObject><Choices is-dropdown="0"><Choice>was taking</Choice><Choice is-correct="1">had taken</Choice><Choice>could take</Choice></Choices><ReferenceObject><Paragraph><PersonName><font face="Verdana" size="2" color="#ffffff">E<TAB></TAB></font></PersonName></Paragraph></ReferenceObject><ReferenceObject><Paragraph><PersonName><font face="Verdana" size="12" color="#000000">4<TAB></TAB></font></PersonName></Paragraph></ReferenceObject><Choices is-dropdown="0"><Choice>were</Choice><Choice>was being</Choice><Choice is-correct="1">was</Choice></Choices><ReferenceObject><Paragraph><PersonName><font face="Verdana" size="2" color="#ffffff">E<TAB></TAB></font></PersonName></Paragraph></ReferenceObject><ReferenceObject><Paragraph><PersonName><font face="Verdana" size="12" color="#000000">5<TAB></TAB></font></PersonName></Paragraph></ReferenceObject><Choices is-dropdown="0"><Choice is-correct="1">hadn't expected</Choice><Choice>didn't expected</Choice><Choice>wasn't expect</Choice></Choices><ReferenceObject><Paragraph><PersonName><font face="Verdana" size="2" color="#ffffff">E<TAB></TAB></font></PersonName></Paragraph></ReferenceObject><ReferenceObject><Paragraph><PersonName><font face="Verdana" size="12" color="#000000">6<TAB></TAB></font></PersonName></Paragraph></ReferenceObject><Choices is-dropdown="0"><Choice>walked</Choice><Choice is-correct="1">was walking</Choice><Choice>had walked</Choice></Choices><ReferenceObject><Paragraph><PersonName><font face="Verdana" size="2" color="#ffffff">E<TAB></TAB></font></PersonName></Paragraph></ReferenceObject><ReferenceObject><Paragraph><PersonName><font face="Verdana" size="12" color="#000000">7<TAB></TAB></font></PersonName></Paragraph></ReferenceObject><Choices is-dropdown="0"><Choice>was never playing</Choice><Choice>never played</Choice><Choice is-correct="1">had never played</Choice></Choices><ReferenceObject><Paragraph><PersonName><font face="Verdana" size="2" color="#ffffff">E<TAB></TAB></font></PersonName></Paragraph></ReferenceObject><ReferenceObject><Paragraph><PersonName><font face="Verdana" size="12" color="#000000">8<TAB></TAB></font></PersonName></Paragraph></ReferenceObject><Choices is-dropdown="0"><Choice>had found</Choice><Choice is-correct="1">found</Choice><Choice>was finding</Choice></Choices><ReferenceObject><Paragraph><PersonName><font face="Verdana" size="2" color="#ffffff">E<TAB></TAB></font></PersonName></Paragraph></ReferenceObject><ReferenceObject><Paragraph><PersonName><font face="Verdana" size="12" color="#000000">9<TAB></TAB></font></PersonName></Paragraph></ReferenceObject><Choices is-dropdown="0"><Choice>had travelled</Choice><Choice>could travel</Choice><Choice is-correct="1">was travelling</Choice></Choices><ReferenceObject><Paragraph><PersonName><font face="Verdana" size="2" color="#ffffff">E<TAB></TAB></font></PersonName></Paragraph></ReferenceObject><ReferenceObject><Paragraph><PersonName><font face="Verdana" size="12" color="#000000">10<TAB></TAB></font></PersonName></Paragraph></ReferenceObject><Choices is-dropdown="0"><Choice is-correct="1">was giving</Choice><Choice>given</Choice><Choice>was given</Choice></Choices></ContentMultipleChoice></MultipleChoice></Activity></Entry></CD-RAT>