<CD-RAT><Entry><HWD>12/3/2/<i>Both, neither, either</i></HWD><Activity><GapFillDropdown><Title><i>Both, either, neither</i></Title><Instruction>Click on the correct word for each gap.</Instruction><ContentGapFillDropdown>My best friend and I are very similar. We <Dropdown><Choice is-correct="1">both </Choice><Choice>either </Choice><Choice>neither </Choice></Dropdown>like sport and we <Dropdown><Choice is-correct="1">both </Choice><Choice>either </Choice><Choice>neither </Choice></Dropdown>play the guitar. <Dropdown><Choice>Both </Choice><Choice>Either </Choice><Choice is-correct="1">Neither </Choice></Dropdown>of us eats meat – we are vegetarians. In fact, we eat <Dropdown><Choice>both </Choice><Choice is-correct="1">either </Choice><Choice>neither </Choice></Dropdown>fish or pasta every day, but sometimes we eat <Dropdown><Choice is-correct="1">both </Choice><Choice>either </Choice><Choice>neither </Choice></Dropdown>on the same day. We always go on holiday together, <Dropdown><Choice>both </Choice><Choice is-correct="1">either </Choice><Choice>neither </Choice></Dropdown>to Iceland or Finland. <Dropdown><Choice>Both </Choice><Choice>Either </Choice><Choice is-correct="1">Neither </Choice></Dropdown>of us likes hot weather, so we prefer cold countries. After school, we <Dropdown><Choice is-correct="1">both </Choice><Choice>either </Choice><Choice>neither </Choice></Dropdown>travelled for a year. Now, we are <Dropdown><Choice is-correct="1">both </Choice><Choice>either </Choice><Choice>neither </Choice></Dropdown>studying history. When we finish university, we will probably become <Dropdown><Choice is-correct="1">both </Choice><Choice is-correct="1">either </Choice><Choice>neither </Choice></Dropdown>teachers or tour guides.</ContentGapFillDropdown></GapFillDropdown></Activity></Entry></CD-RAT>