<CD-RAT><Entry><HWD>2.1 Grammar Practice 1</HWD><Activity><GapFillDropdown layer="1" h="480" w="680" y="10" x="10"><Title alignment="left" isOn="1">Verb patterns 1<br /></Title><Instruction alignment="left" isOn="1">Click on the correct words.<br /></Instruction><ReferenceObject soundIsOn="0" videoIsOn="0" defaultHeight="200" alignment="left" isOn="0" /><ScrollableAssets /><Content>1. Pete is thinking <Dropdown><Score num="1" /><Choice>by applying</Choice><Choice>to apply</Choice><Choice is-correct="1">of applying</Choice></Dropdown> to do a Ph.D.<br />2. If you don&apos;t mind <Dropdown><Score num="1" /><Choice>wait</Choice><Choice>to wait</Choice><Choice is-correct="1">waiting</Choice></Dropdown> five minutes, you can use this computer after me.<br />3. Can you imagine <Dropdown><Score num="1" /><Choice is-correct="1">jumping</Choice><Choice>to jump</Choice><Choice>jump</Choice></Dropdown> out of a helicopter at 1000 feet?<br />4. I&apos;m looking forward <Dropdown><Score num="1" /><Choice>meet</Choice><Choice is-correct="1">to meeting</Choice><Choice>meeting</Choice></Dropdown> my distant cousins next week.<br />5. Morris encouraged his students <Dropdown><Score num="1" /><Choice>for reading</Choice><Choice>reading</Choice><Choice is-correct="1">to read</Choice></Dropdown> widely.<br />6. The government delegation persuaded them <Dropdown><Score num="1" /><Choice>of signing</Choice><Choice is-correct="1">to sign</Choice><Choice>by sign</Choice></Dropdown> the treaty.<br />7. I object <Dropdown><Score num="1" /><Choice>to hand over</Choice><Choice>handing over</Choice><Choice is-correct="1">to handing over</Choice></Dropdown> the research before it&apos;s been ratified.<br />8. They avoided <Dropdown><Score num="1" /><Choice is-correct="1">getting</Choice><Choice>get</Choice><Choice>to get</Choice></Dropdown> caught by wearing masks.<br />9. Hannah recommends <Dropdown><Score num="1" /><Choice>to try</Choice><Choice is-correct="1">trying</Choice><Choice>try</Choice></Dropdown> herbal remedies, if conventional medicine doesn’t work.<br />10. I persuaded <Dropdown><Score num="1" /><Choice is-correct="1">her to send</Choice><Choice>to send</Choice><Choice>her sending</Choice></Dropdown> a proposal to the committee. </Content></GapFillDropdown><Feedback playallOn="1" showAnswersOn="1" animatedFeedbackOn="1" testModeOn="0" instantFeedbackOn="0"><Sounds /></Feedback><GenericActivity hintsNextTo="0" timerIsOn="0" CDPrefsFolder="preferences/" CDPrefsFile="cd.xml"><ActivityCanvas graphicAlpha="100" folder="" file="" colourAlpha="100" colour="transparent" /><SoundLibrary y="10" x="10" isOn="0" /><VideoLibrary h="252" w="385" y="78" x="10" isOn="0" /><Assets /></GenericActivity></Activity></Entry></CD-RAT>